delphin/codecs/dmrstikz.py
delphin_latex-1.0.1.dist-info/LICENSE
delphin_latex-1.0.1.dist-info/METADATA
delphin_latex-1.0.1.dist-info/WHEEL
delphin_latex-1.0.1.dist-info/top_level.txt
delphin_latex-1.0.1.dist-info/RECORD
