Metadata-Version: 2.1
Name: delphin-latex
Version: 1.0.1
Summary: LaTeX exporters for DELPH-IN data.
Home-page: https://github.com/delph-in/delphin-latex
Author: Michael Wayne Goodman
Author-email: goodman.m.w@gmail.com
License: MIT
Keywords: latex delph-in linguistics
Platform: UNKNOWN
Classifier: Development Status :: 5 - Production/Stable
Classifier: Intended Audience :: Developers
Classifier: Intended Audience :: Information Technology
Classifier: Intended Audience :: Science/Research
Classifier: License :: OSI Approved :: MIT License
Classifier: Programming Language :: Python :: 3
Classifier: Programming Language :: Python :: 3.6
Classifier: Programming Language :: Python :: 3.7
Classifier: Programming Language :: Python :: 3.8
Classifier: Programming Language :: Python :: 3.9
Classifier: Topic :: Software Development :: Libraries :: Python Modules
Classifier: Topic :: Text Processing :: Linguistic
Classifier: Topic :: Utilities
Requires-Python: >=3.6
License-File: LICENSE
Requires-Dist: pydelphin (>=1.0.0)
